{"nodes": [{"id": "clients_telegram_card_py", "label": "telegram_card.py", "file_type": "code", "source_file": "clients\\telegram_card.py", "source_location": "L1"}, {"id": "telegram_card_star_rating", "label": "_star_rating()", "file_type": "code", "source_file": "clients\\telegram_card.py", "source_location": "L16"}, {"id": "telegram_card_truncate", "label": "_truncate()", "file_type": "code", "source_file": "clients\\telegram_card.py", "source_location": "L23"}, {"id": "telegram_card_build_movie_card_text", "label": "build_movie_card_text()", "file_type": "code", "source_file": "clients\\telegram_card.py", "source_location": "L29"}, {"id": "telegram_card_build_movie_keyboard", "label": "build_movie_keyboard()", "file_type": "code", "source_file": "clients\\telegram_card.py", "source_location": "L68"}, {"id": "telegram_card_send_single_movie_async", "label": "send_single_movie_async()", "file_type": "code", "source_file": "clients\\telegram_card.py", "source_location": "L88"}, {"id": "telegram_card_send_movies_async", "label": "send_movies_async()", "file_type": "code", "source_file": "clients\\telegram_card.py", "source_location": "L113"}, {"id": "telegram_card_rationale_1", "label": "Shared movie card formatting for Telegram (HTML parse mode).", "file_type": "rationale", "source_file": "clients\\telegram_card.py", "source_location": "L1"}, {"id": "telegram_card_rationale_30", "label": "Build the HTML caption for a single movie card.", "file_type": "rationale", "source_file": "clients\\telegram_card.py", "source_location": "L30"}, {"id": "telegram_card_rationale_69", "label": "Inline keyboard attached to each movie card.", "file_type": "rationale", "source_file": "clients\\telegram_card.py", "source_location": "L69"}, {"id": "telegram_card_rationale_89", "label": "Send a single movie card with its inline keyboard.", "file_type": "rationale", "source_file": "clients\\telegram_card.py", "source_location": "L89"}, {"id": "telegram_card_rationale_118", "label": "Send a list of movie cards, with an optional 'More suggestions' button at the en", "file_type": "rationale", "source_file": "clients\\telegram_card.py", "source_location": "L118"}], "edges": [{"source": "clients_telegram_card_py", "target": "typing", "relation": "imports_from", "confidence": "EXTRACTED", "source_file": "clients\\telegram_card.py", "source_location": "L4", "weight": 1.0}, {"source": "clients_telegram_card_py", "target": "clients_telegram_helpers", "relation": "imports_from", "confidence": "EXTRACTED", "source_file": "clients\\telegram_card.py", "source_location": "L6", "weight": 1.0}, {"source": "clients_telegram_card_py", "target": "models_domain", "relation": "imports_from", "confidence": "EXTRACTED", "source_file": "clients\\telegram_card.py", "source_location": "L7", "weight": 1.0}, {"source": "clients_telegram_card_py", "target": "services_logging_service", "relation": "imports_from", "confidence": "EXTRACTED", "source_file": "clients\\telegram_card.py", "source_location": "L8", "weight": 1.0}, {"source": "clients_telegram_card_py", "target": "telegram_card_star_rating", "relation": "contains", "confidence": "EXTRACTED", "source_file": "clients\\telegram_card.py", "source_location": "L16", "weight": 1.0}, {"source": "clients_telegram_card_py", "target": "telegram_card_truncate", "relation": "contains", "confidence": "EXTRACTED", "source_file": "clients\\telegram_card.py", "source_location": "L23", "weight": 1.0}, {"source": "clients_telegram_card_py", "target": "telegram_card_build_movie_card_text", "relation": "contains", "confidence": "EXTRACTED", "source_file": "clients\\telegram_card.py", "source_location": "L29", "weight": 1.0}, {"source": "clients_telegram_card_py", "target": "telegram_card_build_movie_keyboard", "relation": "contains", "confidence": "EXTRACTED", "source_file": "clients\\telegram_card.py", "source_location": "L68", "weight": 1.0}, {"source": "clients_telegram_card_py", "target": "telegram_card_send_single_movie_async", "relation": "contains", "confidence": "EXTRACTED", "source_file": "clients\\telegram_card.py", "source_location": "L88", "weight": 1.0}, {"source": "clients_telegram_card_py", "target": "telegram_card_send_movies_async", "relation": "contains", "confidence": "EXTRACTED", "source_file": "clients\\telegram_card.py", "source_location": "L113", "weight": 1.0}, {"source": "telegram_card_build_movie_card_text", "target": "telegram_card_star_rating", "relation": "calls", "confidence": "EXTRACTED", "source_file": "clients\\telegram_card.py", "source_location": "L48", "weight": 1.0}, {"source": "telegram_card_build_movie_card_text", "target": "telegram_card_truncate", "relation": "calls", "confidence": "EXTRACTED", "source_file": "clients\\telegram_card.py", "source_location": "L54", "weight": 1.0}, {"source": "telegram_card_send_single_movie_async", "target": "telegram_card_build_movie_card_text", "relation": "calls", "confidence": "EXTRACTED", "source_file": "clients\\telegram_card.py", "source_location": "L90", "weight": 1.0}, {"source": "telegram_card_send_single_movie_async", "target": "telegram_card_build_movie_keyboard", "relation": "calls", "confidence": "EXTRACTED", "source_file": "clients\\telegram_card.py", "source_location": "L91", "weight": 1.0}, {"source": "telegram_card_send_movies_async", "target": "telegram_card_send_single_movie_async", "relation": "calls", "confidence": "EXTRACTED", "source_file": "clients\\telegram_card.py", "source_location": "L124", "weight": 1.0}, {"source": "telegram_card_rationale_1", "target": "clients_telegram_card_py", "relation": "rationale_for", "confidence": "EXTRACTED", "source_file": "clients\\telegram_card.py", "source_location": "L1", "weight": 1.0}, {"source": "telegram_card_rationale_30", "target": "telegram_card_build_movie_card_text", "relation": "rationale_for", "confidence": "EXTRACTED", "source_file": "clients\\telegram_card.py", "source_location": "L30", "weight": 1.0}, {"source": "telegram_card_rationale_69", "target": "telegram_card_build_movie_keyboard", "relation": "rationale_for", "confidence": "EXTRACTED", "source_file": "clients\\telegram_card.py", "source_location": "L69", "weight": 1.0}, {"source": "telegram_card_rationale_89", "target": "telegram_card_send_single_movie_async", "relation": "rationale_for", "confidence": "EXTRACTED", "source_file": "clients\\telegram_card.py", "source_location": "L89", "weight": 1.0}, {"source": "telegram_card_rationale_118", "target": "telegram_card_send_movies_async", "relation": "rationale_for", "confidence": "EXTRACTED", "source_file": "clients\\telegram_card.py", "source_location": "L118", "weight": 1.0}], "raw_calls": [{"caller_nid": "telegram_card_star_rating", "callee": "round", "source_file": "clients\\telegram_card.py", "source_location": "L19"}, {"caller_nid": "telegram_card_truncate", "callee": "len", "source_file": "clients\\telegram_card.py", "source_location": "L24"}, {"caller_nid": "telegram_card_truncate", "callee": "rsplit", "source_file": "clients\\telegram_card.py", "source_location": "L26"}, {"caller_nid": "telegram_card_build_movie_card_text", "callee": "get", "source_file": "clients\\telegram_card.py", "source_location": "L31"}, {"caller_nid": "telegram_card_build_movie_card_text", "callee": "get", "source_file": "clients\\telegram_card.py", "source_location": "L32"}, {"caller_nid": "telegram_card_build_movie_card_text", "callee": "get", "source_file": "clients\\telegram_card.py", "source_location": "L33"}, {"caller_nid": "telegram_card_build_movie_card_text", "callee": "get", "source_file": "clients\\telegram_card.py", "source_location": "L34"}, {"caller_nid": "telegram_card_build_movie_card_text", "callee": "get", "source_file": "clients\\telegram_card.py", "source_location": "L35"}, {"caller_nid": "telegram_card_build_movie_card_text", "callee": "get", "source_file": "clients\\telegram_card.py", "source_location": "L36"}, {"caller_nid": "telegram_card_build_movie_card_text", "callee": "get", "source_file": "clients\\telegram_card.py", "source_location": "L37"}, {"caller_nid": "telegram_card_build_movie_card_text", "callee": "get", "source_file": "clients\\telegram_card.py", "source_location": "L38"}, {"caller_nid": "telegram_card_build_movie_card_text", "callee": "get", "source_file": "clients\\telegram_card.py", "source_location": "L39"}, {"caller_nid": "telegram_card_build_movie_card_text", "callee": "append", "source_file": "clients\\telegram_card.py", "source_location": "L45"}, {"caller_nid": "telegram_card_build_movie_card_text", "callee": "append", "source_file": "clients\\telegram_card.py", "source_location": "L48"}, {"caller_nid": "telegram_card_build_movie_card_text", "callee": "float", "source_file": "clients\\telegram_card.py", "source_location": "L48"}, {"caller_nid": "telegram_card_build_movie_card_text", "callee": "append", "source_file": "clients\\telegram_card.py", "source_location": "L50"}, {"caller_nid": "telegram_card_build_movie_card_text", "callee": "lower", "source_file": "clients\\telegram_card.py", "source_location": "L51"}, {"caller_nid": "telegram_card_build_movie_card_text", "callee": "append", "source_file": "clients\\telegram_card.py", "source_location": "L52"}, {"caller_nid": "telegram_card_build_movie_card_text", "callee": "append", "source_file": "clients\\telegram_card.py", "source_location": "L54"}, {"caller_nid": "telegram_card_build_movie_card_text", "callee": "append", "source_file": "clients\\telegram_card.py", "source_location": "L56"}, {"caller_nid": "telegram_card_build_movie_card_text", "callee": "append", "source_file": "clients\\telegram_card.py", "source_location": "L58"}, {"caller_nid": "telegram_card_build_movie_card_text", "callee": "append", "source_file": "clients\\telegram_card.py", "source_location": "L60"}, {"caller_nid": "telegram_card_build_movie_card_text", "callee": "join", "source_file": "clients\\telegram_card.py", "source_location": "L62"}, {"caller_nid": "telegram_card_build_movie_card_text", "callee": "len", "source_file": "clients\\telegram_card.py", "source_location": "L63"}, {"caller_nid": "telegram_card_build_movie_keyboard", "callee": "str", "source_file": "clients\\telegram_card.py", "source_location": "L70"}, {"caller_nid": "telegram_card_build_movie_keyboard", "callee": "get", "source_file": "clients\\telegram_card.py", "source_location": "L70"}, {"caller_nid": "telegram_card_build_movie_keyboard", "callee": "str", "source_file": "clients\\telegram_card.py", "source_location": "L71"}, {"caller_nid": "telegram_card_build_movie_keyboard", "callee": "get", "source_file": "clients\\telegram_card.py", "source_location": "L71"}, {"caller_nid": "telegram_card_send_single_movie_async", "callee": "get", "source_file": "clients\\telegram_card.py", "source_location": "L93"}, {"caller_nid": "telegram_card_send_single_movie_async", "callee": "get_instance", "source_file": "clients\\telegram_card.py", "source_location": "L97"}, {"caller_nid": "telegram_card_send_single_movie_async", "callee": "send_photo", "source_file": "clients\\telegram_card.py", "source_location": "L98"}, {"caller_nid": "telegram_card_send_single_movie_async", "callee": "warning", "source_file": "clients\\telegram_card.py", "source_location": "L107"}, {"caller_nid": "telegram_card_send_single_movie_async", "callee": "send_message", "source_file": "clients\\telegram_card.py", "source_location": "L110"}, {"caller_nid": "telegram_card_send_movies_async", "callee": "send_message", "source_file": "clients\\telegram_card.py", "source_location": "L120"}, {"caller_nid": "telegram_card_send_movies_async", "callee": "send_message", "source_file": "clients\\telegram_card.py", "source_location": "L132"}]}