{"nodes": [{"id": "tests_test_normalizer_py", "label": "test_normalizer.py", "file_type": "code", "source_file": "tests\\test_normalizer.py", "source_location": "L1"}, {"id": "test_normalizer_test_normalize_input_message", "label": "test_normalize_input_message()", "file_type": "code", "source_file": "tests\\test_normalizer.py", "source_location": "L24"}, {"id": "test_normalizer_test_normalize_input_callback", "label": "test_normalize_input_callback()", "file_type": "code", "source_file": "tests\\test_normalizer.py", "source_location": "L46"}, {"id": "test_normalizer_test_detect_intent_basic_commands", "label": "test_detect_intent_basic_commands()", "file_type": "code", "source_file": "tests\\test_normalizer.py", "source_location": "L69"}, {"id": "test_normalizer_test_detect_intent_question_state", "label": "test_detect_intent_question_state()", "file_type": "code", "source_file": "tests\\test_normalizer.py", "source_location": "L78"}, {"id": "test_normalizer_test_detect_intent_fallback", "label": "test_detect_intent_fallback()", "file_type": "code", "source_file": "tests\\test_normalizer.py", "source_location": "L84"}, {"id": "test_normalizer_rationale_1", "label": "Placeholder tests for a normalizer module.  The original file used `from .norm", "file_type": "rationale", "source_file": "tests\\test_normalizer.py", "source_location": "L1"}], "edges": [{"source": "tests_test_normalizer_py", "target": "pytest", "relation": "imports", "confidence": "EXTRACTED", "source_file": "tests\\test_normalizer.py", "source_location": "L15", "weight": 1.0}, {"source": "tests_test_normalizer_py", "target": "test_normalizer_test_normalize_input_message", "relation": "contains", "confidence": "EXTRACTED", "source_file": "tests\\test_normalizer.py", "source_location": "L24", "weight": 1.0}, {"source": "tests_test_normalizer_py", "target": "test_normalizer_test_normalize_input_callback", "relation": "contains", "confidence": "EXTRACTED", "source_file": "tests\\test_normalizer.py", "source_location": "L46", "weight": 1.0}, {"source": "tests_test_normalizer_py", "target": "test_normalizer_test_detect_intent_basic_commands", "relation": "contains", "confidence": "EXTRACTED", "source_file": "tests\\test_normalizer.py", "source_location": "L69", "weight": 1.0}, {"source": "tests_test_normalizer_py", "target": "test_normalizer_test_detect_intent_question_state", "relation": "contains", "confidence": "EXTRACTED", "source_file": "tests\\test_normalizer.py", "source_location": "L78", "weight": 1.0}, {"source": "tests_test_normalizer_py", "target": "test_normalizer_test_detect_intent_fallback", "relation": "contains", "confidence": "EXTRACTED", "source_file": "tests\\test_normalizer.py", "source_location": "L84", "weight": 1.0}, {"source": "test_normalizer_rationale_1", "target": "tests_test_normalizer_py", "relation": "rationale_for", "confidence": "EXTRACTED", "source_file": "tests\\test_normalizer.py", "source_location": "L1", "weight": 1.0}], "raw_calls": [{"caller_nid": "test_normalizer_test_normalize_input_message", "callee": "normalize_input", "source_file": "tests\\test_normalizer.py", "source_location": "L35"}, {"caller_nid": "test_normalizer_test_normalize_input_callback", "callee": "normalize_input", "source_file": "tests\\test_normalizer.py", "source_location": "L60"}, {"caller_nid": "test_normalizer_test_detect_intent_basic_commands", "callee": "detect_intent", "source_file": "tests\\test_normalizer.py", "source_location": "L70"}, {"caller_nid": "test_normalizer_test_detect_intent_basic_commands", "callee": "detect_intent", "source_file": "tests\\test_normalizer.py", "source_location": "L71"}, {"caller_nid": "test_normalizer_test_detect_intent_basic_commands", "callee": "detect_intent", "source_file": "tests\\test_normalizer.py", "source_location": "L72"}, {"caller_nid": "test_normalizer_test_detect_intent_basic_commands", "callee": "detect_intent", "source_file": "tests\\test_normalizer.py", "source_location": "L73"}, {"caller_nid": "test_normalizer_test_detect_intent_basic_commands", "callee": "detect_intent", "source_file": "tests\\test_normalizer.py", "source_location": "L74"}, {"caller_nid": "test_normalizer_test_detect_intent_question_state", "callee": "detect_intent", "source_file": "tests\\test_normalizer.py", "source_location": "L80"}, {"caller_nid": "test_normalizer_test_detect_intent_fallback", "callee": "detect_intent", "source_file": "tests\\test_normalizer.py", "source_location": "L85"}]}