{"nodes": [{"id": "utils_formatters_py", "label": "formatters.py", "file_type": "code", "source_file": "utils\\formatters.py", "source_location": "L1"}, {"id": "formatters_format_history_list", "label": "format_history_list()", "file_type": "code", "source_file": "utils\\formatters.py", "source_location": "L13"}, {"id": "formatters_format_watchlist_list", "label": "format_watchlist_list()", "file_type": "code", "source_file": "utils\\formatters.py", "source_location": "L42"}, {"id": "formatters_rationale_1", "label": "Presentation-layer formatting helpers for history and watchlist.  These live i", "file_type": "rationale", "source_file": "utils\\formatters.py", "source_location": "L1"}, {"id": "formatters_rationale_18", "label": "Return an HTML-formatted string for a page of history rows.", "file_type": "rationale", "source_file": "utils\\formatters.py", "source_location": "L18"}, {"id": "formatters_rationale_47", "label": "Return an HTML-formatted string for a page of watchlist rows.", "file_type": "rationale", "source_file": "utils\\formatters.py", "source_location": "L47"}], "edges": [{"source": "utils_formatters_py", "target": "typing", "relation": "imports_from", "confidence": "EXTRACTED", "source_file": "utils\\formatters.py", "source_location": "L8", "weight": 1.0}, {"source": "utils_formatters_py", "target": "formatters_format_history_list", "relation": "contains", "confidence": "EXTRACTED", "source_file": "utils\\formatters.py", "source_location": "L13", "weight": 1.0}, {"source": "utils_formatters_py", "target": "formatters_format_watchlist_list", "relation": "contains", "confidence": "EXTRACTED", "source_file": "utils\\formatters.py", "source_location": "L42", "weight": 1.0}, {"source": "formatters_rationale_1", "target": "utils_formatters_py", "relation": "rationale_for", "confidence": "EXTRACTED", "source_file": "utils\\formatters.py", "source_location": "L1", "weight": 1.0}, {"source": "formatters_rationale_18", "target": "formatters_format_history_list", "relation": "rationale_for", "confidence": "EXTRACTED", "source_file": "utils\\formatters.py", "source_location": "L18", "weight": 1.0}, {"source": "formatters_rationale_47", "target": "formatters_format_watchlist_list", "relation": "rationale_for", "confidence": "EXTRACTED", "source_file": "utils\\formatters.py", "source_location": "L47", "weight": 1.0}], "raw_calls": [{"caller_nid": "formatters_format_history_list", "callee": "enumerate", "source_file": "utils\\formatters.py", "source_location": "L26"}, {"caller_nid": "formatters_format_history_list", "callee": "get", "source_file": "utils\\formatters.py", "source_location": "L27"}, {"caller_nid": "formatters_format_history_list", "callee": "get", "source_file": "utils\\formatters.py", "source_location": "L28"}, {"caller_nid": "formatters_format_history_list", "callee": "get", "source_file": "utils\\formatters.py", "source_location": "L29"}, {"caller_nid": "formatters_format_history_list", "callee": "get", "source_file": "utils\\formatters.py", "source_location": "L30"}, {"caller_nid": "formatters_format_history_list", "callee": "append", "source_file": "utils\\formatters.py", "source_location": "L38"}, {"caller_nid": "formatters_format_history_list", "callee": "join", "source_file": "utils\\formatters.py", "source_location": "L39"}, {"caller_nid": "formatters_format_watchlist_list", "callee": "enumerate", "source_file": "utils\\formatters.py", "source_location": "L55"}, {"caller_nid": "formatters_format_watchlist_list", "callee": "get", "source_file": "utils\\formatters.py", "source_location": "L56"}, {"caller_nid": "formatters_format_watchlist_list", "callee": "get", "source_file": "utils\\formatters.py", "source_location": "L57"}, {"caller_nid": "formatters_format_watchlist_list", "callee": "get", "source_file": "utils\\formatters.py", "source_location": "L58"}, {"caller_nid": "formatters_format_watchlist_list", "callee": "append", "source_file": "utils\\formatters.py", "source_location": "L64"}, {"caller_nid": "formatters_format_watchlist_list", "callee": "join", "source_file": "utils\\formatters.py", "source_location": "L65"}]}